{"schema_version":2,"corrections":[{"name":"ttbar_corr_bdtshape_2022EE","description":"ttbar correction bdtshape for 2022EE","version":1,"inputs":[{"name":"bdtshape","type":"real","description":"bdtshape"},{"name":"systematic","type":"string","description":"Systematic variation"}],"output":{"name":"weight","type":"real","description":"ttbar efficiency"},"data":{"nodetype":"category","input":"systematic","content":[{"key":"nominal","value":{"nodetype":"binning","input":"bdtshape","edges":[0.0,0.0299999,0.6374999,0.9074999,1.0],"content":[1.2691456308877718,2.286901822047879,2.601980515847398,3.079544400156774],"flow":1.0}},{"key":"stat_up","value":{"nodetype":"binning","input":"bdtshape","edges":[0.0,0.0299999,0.6374999,0.9074999,1.0],"content":[0.2814265522332675,0.07416908539317912,0.1496221481034814,0.43905465604378247],"flow":1.0}},{"key":"stat_dn","value":{"nodetype":"binning","input":"bdtshape","edges":[0.0,0.0299999,0.6374999,0.9074999,1.0],"content":[0.23380516992656153,0.07187390624404832,0.14168831974818596,0.38705745884255816],"flow":1.0}}]}}]}