{
    "WP1_pt200to250": {
        "jer": {
            "high": 0.0022907137213898075,
            "low": 0.0009346040383966157
        },
        "jes": {
            "high": 0.005247597308214197,
            "low": 0.0047251501333550865
        },
        "fracBB": {
            "high": 0.005407978151928745,
            "low": 0.00917368974735513
        },
        "stats": {
            "high": 0.04113116471382816,
            "low": 0.03751897695833506
        },
        "fracLight": {
            "high": 0.00822718512626565,
            "low": 0.008463334428776744
        },
        "pu": {
            "high": 0.0018469435553556772,
            "low": 0.0005340443666242461
        },
        "fracCC": {
            "high": 0.010923811099353949,
            "low": 0.01644020195002789
        },
        "psWeightIsr": {
            "high": 0.0,
            "low": 0.0
        },
        "lumi_13TeV": {
            "high": 0.0005393659036985668,
            "low": 0.0
        },
        "l1PreFiring": {
            "high": 0.0,
            "low": 0.0
        },
        "psWeightFsr": {
            "high": 0.0,
            "low": 0.0015632881565722924
        },
        "extSfBDTVariation": {
            "high": 0.0462001680663063,
            "low": 0.022146256777120607
        },
        "extVarRwgt": {
            "high": 0.07751307152735243,
            "low": 0.07751307152735243
        },
        "final": {
            "central": 1.0807148731293303,
            "high": 0.10042283277478554,
            "low": 0.0914241755270742
        }
    },
    "WP1_pt250to300": {
        "jer": {
            "high": 0.0007716023704093468,
            "low": 0.0003910620836825719
        },
        "jes": {
            "high": 0.004856219629366873,
            "low": 0.005072433442758414
        },
        "fracBB": {
            "high": 0.0067334950817414824,
            "low": 0.007388065692351667
        },
        "stats": {
            "high": 0.034877067226255054,
            "low": 0.032867332272754624
        },
        "fracLight": {
            "high": 0.006558576634042498,
            "low": 0.007250065846678372
        },
        "pu": {
            "high": 0.0057393511193529305,
            "low": 0.004768862392944135
        },
        "fracCC": {
            "high": 0.010224545669651475,
            "low": 0.01030608828436633
        },
        "psWeightIsr": {
            "high": 0.0,
            "low": 0.0
        },
        "lumi_13TeV": {
            "high": 0.000414713121724286,
            "low": 0.00019985305894306633
        },
        "l1PreFiring": {
            "high": 0.0,
            "low": 0.0
        },
        "psWeightFsr": {
            "high": 0.0,
            "low": 0.0013676317546137183
        },
        "extSfBDTVariation": {
            "high": 0.019233683342606105,
            "low": 0.015528344933103481
        },
        "extVarRwgt": {
            "high": 0.05428495636615027,
            "low": 0.05428495636615027
        },
        "final": {
            "central": 1.0459648626381777,
            "high": 0.06914818114387894,
            "low": 0.06732120659133724
        }
    },
    "WP1_pt300to400": {
        "jer": {
            "high": 0.00017026449626776768,
            "low": 0.00020276050521127287
        },
        "jes": {
            "high": 0.003942676045968221,
            "low": 0.004713720641558811
        },
        "fracBB": {
            "high": 0.0064482365985711375,
            "low": 0.006615817017265915
        },
        "stats": {
            "high": 0.016906992417818012,
            "low": 0.01666496278138796
        },
        "fracLight": {
            "high": 0.003189807371222165,
            "low": 0.003983479638355782
        },
        "pu": {
            "high": 0.001351560018275847,
            "low": 0.0018037598197596942
        },
        "fracCC": {
            "high": 0.010305669611012985,
            "low": 0.010189195242172636
        },
        "psWeightIsr": {
            "high": 0.0,
            "low": 0.0
        },
        "lumi_13TeV": {
            "high": 0.0,
            "low": 0.0
        },
        "l1PreFiring": {
            "high": 0.0,
            "low": 0.0
        },
        "psWeightFsr": {
            "high": 0.004077138813761254,
            "low": 0.0007467476858087435
        },
        "extSfBDTVariation": {
            "high": 0.03856262819246261,
            "low": 0.034264002151297386
        },
        "extVarRwgt": {
            "high": 0.05410076579305256,
            "low": 0.05410076579305256
        },
        "final": {
            "central": 1.1240165168715244,
            "high": 0.06994135539695681,
            "low": 0.0675881297188444
        }
    },
    "WP1_pt400to500": {
        "jer": {
            "high": 0.00044045596864267255,
            "low": 0.0010403823676981045
        },
        "jes": {
            "high": 0.0009753383223545276,
            "low": 0.0020743121650537
        },
        "fracBB": {
            "high": 0.0046364803150556935,
            "low": 0.0024692667743321938
        },
        "stats": {
            "high": 0.015538839745235622,
            "low": 0.016461370996025737
        },
        "fracLight": {
            "high": 0.0015113212576832967,
            "low": 0.0
        },
        "pu": {
            "high": 0.003025260927398371,
            "low": 0.0026924456991617315
        },
        "fracCC": {
            "high": 0.005893091535220423,
            "low": 0.0038928503435064848
        },
        "psWeightIsr": {
            "high": 0.0,
            "low": 0.0
        },
        "lumi_13TeV": {
            "high": 0.0008228304606291318,
            "low": 0.0
        },
        "l1PreFiring": {
            "high": 0.0,
            "low": 0.0
        },
        "psWeightFsr": {
            "high": 0.006063970391127114,
            "low": 0.0
        },
        "extSfBDTVariation": {
            "high": 0.033443715668346204,
            "low": 0.02921631612939368
        },
        "extVarRwgt": {
            "high": 0.0586233538915788,
            "low": 0.0586233538915788
        },
        "final": {
            "central": 1.1193850066610203,
            "high": 0.0700206478560611,
            "low": 0.06770311279120962
        }
    },
    "WP1_pt500to100000": {
        "jer": {
            "high": 0.00014886495890874816,
            "low": 0.0
        },
        "jes": {
            "high": 0.0016679933353426718,
            "low": 0.0011201564460585917
        },
        "fracBB": {
            "high": 0.005434221565843244,
            "low": 0.0031194411292327228
        },
        "stats": {
            "high": 0.012973157827720794,
            "low": 0.014500894089115368
        },
        "fracLight": {
            "high": 0.0010909775734719252,
            "low": 0.0007883519502430958
        },
        "pu": {
            "high": 0.002150552498008417,
            "low": 0.002178661146234617
        },
        "fracCC": {
            "high": 0.005898152088985167,
            "low": 0.0041763228887561985
        },
        "psWeightIsr": {
            "high": 0.0,
            "low": 0.0
        },
        "lumi_13TeV": {
            "high": 7.392009289600198e-05,
            "low": 0.0001137650830607297
        },
        "l1PreFiring": {
            "high": 0.0,
            "low": 0.0
        },
        "psWeightFsr": {
            "high": 1.896556554713305e-05,
            "low": 0.00023897591926126923
        },
        "extSfBDTVariation": {
            "high": 0.03309384805835875,
            "low": 0.03143132221195457
        },
        "extVarRwgt": {
            "high": 0.04160692444975611,
            "low": 0.04160692444975611
        },
        "final": {
            "central": 1.106034212707907,
            "high": 0.05538579260171272,
            "low": 0.05443531297107028
        }
    },
    "WP2_pt200to250": {
        "jer": {
            "high": 0.014065469641854055,
            "low": 0.0024703296272693053
        },
        "jes": {
            "high": 0.009412547157070995,
            "low": 0.016371367774218423
        },
        "fracBB": {
            "high": 0.008705888384064563,
            "low": 0.003989243770951695
        },
        "stats": {
            "high": 0.06471076644058671,
            "low": 0.06008052774722772
        },
        "fracLight": {
            "high": 0.00800991215441636,
            "low": 0.007865284495671497
        },
        "pu": {
            "high": 0.01317035844884117,
            "low": 0.007489561480579979
        },
        "fracCC": {
            "high": 0.0,
            "low": 0.005327105506102154
        },
        "psWeightIsr": {
            "high": 0.0,
            "low": 0.0
        },
        "lumi_13TeV": {
            "high": 9.545939666663921e-05,
            "low": 0.0004424984654531858
        },
        "l1PreFiring": {
            "high": 0.0,
            "low": 0.0
        },
        "psWeightFsr": {
            "high": 0.0,
            "low": 0.0008255938889641121
        },
        "extSfBDTVariation": {
            "high": 0.07612785852030254,
            "low": 0.1256671504912572
        },
        "extVarRwgt": {
            "high": 0.011826551820401598,
            "low": 0.011826551820401598
        },
        "final": {
            "central": 0.775965869915043,
            "high": 0.10354664955245557,
            "low": 0.14134716066010058
        }
    },
    "WP2_pt250to300": {
        "jer": {
            "high": 0.001707235447115274,
            "low": 0.0011642747093736294
        },
        "jes": {
            "high": 0.010227792703762588,
            "low": 0.009732819568837656
        },
        "fracBB": {
            "high": 0.008357229641682338,
            "low": 0.008306982896177541
        },
        "stats": {
            "high": 0.058938252046998096,
            "low": 0.05643035671120977
        },
        "fracLight": {
            "high": 0.010928624188197995,
            "low": 0.01132637661270877
        },
        "pu": {
            "high": 0.007131300548299986,
            "low": 0.0059484319632709904
        },
        "fracCC": {
            "high": 0.015781436227241638,
            "low": 0.014065888354668711
        },
        "psWeightIsr": {
            "high": 0.0,
            "low": 0.0
        },
        "lumi_13TeV": {
            "high": 0.00026576886432106046,
            "low": 0.0006078857992703032
        },
        "l1PreFiring": {
            "high": 0.0,
            "low": 0.0
        },
        "psWeightFsr": {
            "high": 0.0025233456301805017,
            "low": 0.0
        },
        "extSfBDTVariation": {
            "high": 0.033730345192119426,
            "low": 0.06051470356317231
        },
        "extVarRwgt": {
            "high": 0.082115156182894,
            "low": 0.082115156182894
        },
        "final": {
            "central": 0.9405359290919756,
            "high": 0.10935035532467675,
            "low": 0.11878903441120774
        }
    },
    "WP2_pt300to400": {
        "jer": {
            "high": 0.0008144876821594633,
            "low": 0.00035486064369056805
        },
        "jes": {
            "high": 0.0013560356056897432,
            "low": 0.008196913525321722
        },
        "fracBB": {
            "high": 0.005530566318614157,
            "low": 0.0035411659711765686
        },
        "stats": {
            "high": 0.03427277635569648,
            "low": 0.042248426895551416
        },
        "fracLight": {
            "high": 0.0036471006759411107,
            "low": 0.0008277437764368347
        },
        "pu": {
            "high": 0.006536930634026315,
            "low": 0.005469720611549449
        },
        "fracCC": {
            "high": 0.009456360790508116,
            "low": 0.0029358926247406813
        },
        "psWeightIsr": {
            "high": 0.0,
            "low": 0.0
        },
        "lumi_13TeV": {
            "high": 0.00016744828822481852,
            "low": 0.0
        },
        "l1PreFiring": {
            "high": 0.0,
            "low": 0.0
        },
        "psWeightFsr": {
            "high": 0.0006842287507715564,
            "low": 0.0
        },
        "extSfBDTVariation": {
            "high": 0.037217850673174145,
            "low": 0.03633974257837642
        },
        "extVarRwgt": {
            "high": 0.028615951612086743,
            "low": 0.028615951612086743
        },
        "final": {
            "central": 0.8476331081410163,
            "high": 0.0596465041208941,
            "low": 0.06358521998840845
        }
    },
    "WP2_pt400to500": {
        "jer": {
            "high": 0.0013280060798104157,
            "low": 0.019493335043342924
        },
        "jes": {
            "high": 0.007839575686997686,
            "low": 0.02757931961723317
        },
        "fracBB": {
            "high": 0.002746161824204399,
            "low": 0.0269312754080068
        },
        "stats": {
            "high": 0.0347262603315458,
            "low": 0.035433050921610754
        },
        "fracLight": {
            "high": 0.00153609881058491,
            "low": 0.020391728417149355
        },
        "pu": {
            "high": 0.0011746484632586263,
            "low": 0.0012501270760585477
        },
        "fracCC": {
            "high": 0.0033032086267583117,
            "low": 0.0024581942829489554
        },
        "psWeightIsr": {
            "high": 0.0,
            "low": 0.0
        },
        "lumi_13TeV": {
            "high": 0.0001763492272994909,
            "low": 0.0
        },
        "l1PreFiring": {
            "high": 0.0,
            "low": 0.0
        },
        "psWeightFsr": {
            "high": 0.0,
            "low": 0.0012405445213344087
        },
        "extSfBDTVariation": {
            "high": 0.04697889431384026,
            "low": 0.019097266553266837
        },
        "extVarRwgt": {
            "high": 0.028688441978561685,
            "low": 0.028688441978561685
        },
        "final": {
            "central": 0.7948552912177789,
            "high": 0.06573584422409137,
            "low": 0.06880251606140826
        }
    },
    "WP2_pt500to100000": {
        "jer": {
            "high": 0.0021005231475142035,
            "low": 0.0018133463049007771
        },
        "jes": {
            "high": 0.005007605559007435,
            "low": 0.004376977972043435
        },
        "fracBB": {
            "high": 0.002495422533136853,
            "low": 0.002395270192335942
        },
        "stats": {
            "high": 0.030733401169365737,
            "low": 0.029882846017335485
        },
        "fracLight": {
            "high": 0.001413717966259446,
            "low": 0.0016547338280767721
        },
        "pu": {
            "high": 0.0034899128902433447,
            "low": 0.0026622136808787215
        },
        "fracCC": {
            "high": 0.005232829296292424,
            "low": 0.004791925042003317
        },
        "psWeightIsr": {
            "high": 0.0,
            "low": 0.0
        },
        "lumi_13TeV": {
            "high": 0.0004330347648906778,
            "low": 0.0
        },
        "l1PreFiring": {
            "high": 0.0,
            "low": 0.0
        },
        "psWeightFsr": {
            "high": 0.0,
            "low": 0.0010147661602016892
        },
        "extSfBDTVariation": {
            "high": 0.02563462168260948,
            "low": 0.0470441709418927
        },
        "extVarRwgt": {
            "high": 0.04154732137484762,
            "low": 0.04154732137484762
        },
        "final": {
            "central": 0.8897300714486738,
            "high": 0.058347350934399786,
            "low": 0.06995928194684621
        }
    },
    "WP3_pt200to250": {
        "jer": {
            "high": 0.00025786534303150286,
            "low": 0.0002042188748998394
        },
        "jes": {
            "high": 0.001155366103080801,
            "low": 0.0016056741000041248
        },
        "fracBB": {
            "high": 0.007781473703404784,
            "low": 0.007130930497946442
        },
        "stats": {
            "high": 0.10502135053039208,
            "low": 0.09032713879169219
        },
        "fracLight": {
            "high": 0.0038395496372722647,
            "low": 0.003216114774647331
        },
        "pu": {
            "high": 0.0009749358809628042,
            "low": 0.0014509500882734611
        },
        "fracCC": {
            "high": 0.013517287098718278,
            "low": 0.011215304113127602
        },
        "psWeightIsr": {
            "high": 0.0,
            "low": 0.0
        },
        "lumi_13TeV": {
            "high": 0.0004024570919980201,
            "low": 0.0011524376061276319
        },
        "l1PreFiring": {
            "high": 0.0,
            "low": 0.0
        },
        "psWeightFsr": {
            "high": 0.003824497818129573,
            "low": 0.0
        },
        "extSfBDTVariation": {
            "high": 0.07640074414086556,
            "low": 0.08966879624638338
        },
        "extVarRwgt": {
            "high": 0.06762446539842382,
            "low": 0.06762446539842382
        },
        "final": {
            "central": 0.7623395108818105,
            "high": 0.14735934730604025,
            "low": 0.1447540077351795
        }
    },
    "WP3_pt250to300": {
        "jer": {
            "high": 0.00803409206075178,
            "low": 0.002632613352936591
        },
        "jes": {
            "high": 0.00883753156046553,
            "low": 0.008117696566477876
        },
        "fracBB": {
            "high": 0.002260781695086572,
            "low": 0.0028781332604454085
        },
        "stats": {
            "high": 0.11961954858415924,
            "low": 0.10247729980803899
        },
        "fracLight": {
            "high": 0.004774278868500427,
            "low": 0.010720040180124367
        },
        "pu": {
            "high": 0.010734636124661889,
            "low": 0.00539050076249428
        },
        "fracCC": {
            "high": 0.006732231309317643,
            "low": 0.0019475521678824345
        },
        "psWeightIsr": {
            "high": 0.0,
            "low": 0.0
        },
        "lumi_13TeV": {
            "high": 0.0011272788826734304,
            "low": 0.0
        },
        "l1PreFiring": {
            "high": 0.0,
            "low": 0.0
        },
        "psWeightFsr": {
            "high": 0.005823237160886406,
            "low": 0.0
        },
        "extSfBDTVariation": {
            "high": 0.030504774103544456,
            "low": 0.03929614839446492
        },
        "extVarRwgt": {
            "high": 0.02170374898190086,
            "low": 0.02170374898190086
        },
        "final": {
            "central": 0.7398609699995101,
            "high": 0.12679400631815324,
            "low": 0.11277473461784042
        }
    },
    "WP3_pt300to400": {
        "jer": {
            "high": 0.000644464708103321,
            "low": 0.0
        },
        "jes": {
            "high": 0.008010414059177299,
            "low": 0.01799888123608943
        },
        "fracBB": {
            "high": 0.0052911803498104796,
            "low": 0.003147992196796158
        },
        "stats": {
            "high": 0.0707289461601891,
            "low": 0.08300334396161768
        },
        "fracLight": {
            "high": 0.002856844230506644,
            "low": 0.0027020916151940734
        },
        "pu": {
            "high": 0.001968172646610102,
            "low": 0.001720314299326892
        },
        "fracCC": {
            "high": 0.005675135641337706,
            "low": 0.0035491262058198795
        },
        "psWeightIsr": {
            "high": 0.0,
            "low": 0.0
        },
        "lumi_13TeV": {
            "high": 0.000291458910065631,
            "low": 0.00035310607657572797
        },
        "l1PreFiring": {
            "high": 0.0,
            "low": 0.0
        },
        "psWeightFsr": {
            "high": 0.0,
            "low": 0.00285325793005698
        },
        "extSfBDTVariation": {
            "high": 0.048352935007488634,
            "low": 0.028304817710444886
        },
        "extVarRwgt": {
            "high": 0.011678083340595169,
            "low": 0.011678083340595169
        },
        "final": {
            "central": 0.7431393061416791,
            "high": 0.08721865768573571,
            "low": 0.0905099209613851
        }
    },
    "WP3_pt400to500": {
        "jer": {
            "high": 0.00125908338910706,
            "low": 0.0015901424463780121
        },
        "jes": {
            "high": 0.0,
            "low": 0.0
        },
        "fracBB": {
            "high": 0.004145475219503046,
            "low": 0.0025409183016348287
        },
        "stats": {
            "high": 0.060412070845681676,
            "low": 0.06023982762240909
        },
        "fracLight": {
            "high": 0.00039332141939480585,
            "low": 0.0012760742481446922
        },
        "pu": {
            "high": 0.002486841766273341,
            "low": 0.0029036305281784744
        },
        "fracCC": {
            "high": 0.0049119766463862425,
            "low": 0.0022100475040042066
        },
        "psWeightIsr": {
            "high": 0.0,
            "low": 0.0
        },
        "lumi_13TeV": {
            "high": 0.0006957917059347694,
            "low": 0.0011384841963550107
        },
        "l1PreFiring": {
            "high": 0.0,
            "low": 0.0
        },
        "psWeightFsr": {
            "high": 0.0,
            "low": 0.002998603927039081
        },
        "extSfBDTVariation": {
            "high": 0.036220492731642726,
            "low": 0.049190490848964014
        },
        "extVarRwgt": {
            "high": 0.014206648210881245,
            "low": 0.014206648210881245
        },
        "final": {
            "central": 0.859657510420142,
            "high": 0.07214341528370856,
            "low": 0.07927399434448702
        }
    },
    "WP3_pt500to100000": {
        "jer": {
            "high": 0.001515563479064126,
            "low": 0.003310242677976465
        },
        "jes": {
            "high": 0.002337779184858854,
            "low": 0.006260168922188769
        },
        "fracBB": {
            "high": 0.002482797624403863,
            "low": 0.0005047612319470161
        },
        "stats": {
            "high": 0.06337368585662384,
            "low": 0.05192661407815424
        },
        "fracLight": {
            "high": 0.0016737762148693123,
            "low": 0.007832927013899102
        },
        "pu": {
            "high": 0.0018602507163833714,
            "low": 0.0
        },
        "fracCC": {
            "high": 0.00028445878945290666,
            "low": 0.0046611885301040675
        },
        "psWeightIsr": {
            "high": 0.0,
            "low": 0.0
        },
        "lumi_13TeV": {
            "high": 0.000947745846589474,
            "low": 0.0
        },
        "l1PreFiring": {
            "high": 0.0,
            "low": 0.0
        },
        "psWeightFsr": {
            "high": 0.002185325525231436,
            "low": 0.0
        },
        "extSfBDTVariation": {
            "high": 0.0,
            "low": 0.03303702750914993
        },
        "extVarRwgt": {
            "high": 0.018382299462089913,
            "low": 0.018382299462089913
        },
        "final": {
            "central": 0.78931353069415,
            "high": 0.06508654480213191,
            "low": 0.06523586968492308
        }
    }
}
